rocketchat/__init__.py
rocketchat/api.py
rocketchat/calls/__init__.py
rocketchat/calls/base.py
rocketchat/calls/auth/__init__.py
rocketchat/calls/auth/get_me.py
rocketchat/calls/auth/logout.py
rocketchat/calls/channels/__init__.py
rocketchat/calls/channels/create_public_room.py
rocketchat/calls/channels/delete_public_room.py
rocketchat/calls/channels/get_history.py
rocketchat/calls/channels/get_public_rooms.py
rocketchat/calls/channels/get_room_info.py
rocketchat/calls/chat/__init__.py
rocketchat/calls/chat/send_message.py
rocketchat/calls/groups/__init__.py
rocketchat/calls/groups/get_private_room_history.py
rocketchat/calls/groups/get_private_room_info.py
rocketchat/calls/groups/get_private_rooms.py
rocketchat/calls/groups/get_room_id.py
rocketchat/calls/groups/set_room_topic.py
rocketchat/calls/groups/upload_file.py
rocketchat/calls/im/__init__.py
rocketchat/calls/im/close_room.py
rocketchat/calls/im/create_room.py
rocketchat/calls/im/get_history.py
rocketchat/calls/im/get_rooms.py
rocketchat/calls/im/open_room.py
rocketchat/calls/users/__init__.py
rocketchat/calls/users/create_user.py
rocketchat/calls/users/delete_user.py
rocketchat/calls/users/get_user_info.py
rocketchat/calls/users/get_users.py
tests/__init__.py
tests/data.py
tests/test_api.py
rocket_python-1.3.4.dist-info/AUTHORS.txt
rocket_python-1.3.4.dist-info/LICENSE
rocket_python-1.3.4.dist-info/METADATA
rocket_python-1.3.4.dist-info/WHEEL
rocket_python-1.3.4.dist-info/top_level.txt
rocket_python-1.3.4.dist-info/RECORD
