Metadata-Version: 2.1
Name: rocket-python
Version: 1.3.4
Summary: RocketChat API with Python
Home-page: https://github.com/Pipoline/rocket-python
Author: Derek Stegelman, Peter Gonda
License: MIT
Keywords: rocketchat
Classifier: Development Status :: 5 - Production/Stable
Classifier: Intended Audience :: Developers
Classifier: Natural Language :: English
Classifier: Operating System :: OS Independent
Classifier: Programming Language :: Python
Classifier: Topic :: Utilities
Classifier: Programming Language :: Python :: 2
Classifier: Programming Language :: Python :: 3
Classifier: License :: OSI Approved :: MIT License
License-File: LICENSE
License-File: AUTHORS.txt
Requires-Dist: requests (<3.0,>=2.0.0)
